Metadata-Version: 1.0
Name: jobby
Version: 0.0.0
Summary: Runs jobs in the background
Home-page: http://github.com/nilakshdas/jobby
Author: Nilaksh Das
Author-email: UNKNOWN
License: MIT
Platform: UNKNOWN
